{
  "version": 3,
  "updatedAt": "2026-07-17T18:19:07.443Z",
  "lotteries": [
    {
      "externalId": "https://livepocket.jp/e/eq0_2",
      "shop": "フタバ図書 TSUTAYA 海田店",
      "product": "ポケモンカードゲーム　MEGAスターターセットex　イーブイex",
      "type": "店舗",
      "area": "広島県",
      "status": "open",
      "url": "https://livepocket.jp/e/eq0_2",
      "applyStartDate": "2026-07-17",
      "applyStartTime": "12:00",
      "applyEndDate": "2026-07-23",
      "applyEndTime": "21:59",
      "resultStartDate": "2026-07-24",
      "resultStartTime": "12:00",
      "resultEndDate": "",
      "resultEndTime": "",
      "resultNote": "予定",
      "purchaseStartDate": "2026-07-31",
      "purchaseStartTime": "",
      "purchaseEndDate": "2026-08-02",
      "purchaseEndTime": "21:59",
      "destinationType": "direct",
      "appName": "",
      "appUrl": "",
      "fallbackUrl": "",
      "instructions": "",
      "memo": "LivePocket専用APIから自動取得",
      "manualEntry": true,
      "adminPublished": true,
      "verified": true,
      "confidence": 0.99,
      "collectedAt": "2026-07-17T18:19:07.051Z",
      "createdAt": "2026-07-17T18:19:07.160Z",
      "updatedAt": "2026-07-17T18:19:07.160Z"
    }
  ],
  "deleted": []
}
